eazypredict/EazyClassifier.py
eazypredict/EazyRegressor.py
eazypredict/__init__.py
eazypredict-0.2.1.dist-info/AUTHORS.md
eazypredict-0.2.1.dist-info/LICENSE.txt
eazypredict-0.2.1.dist-info/METADATA
eazypredict-0.2.1.dist-info/WHEEL
eazypredict-0.2.1.dist-info/top_level.txt
eazypredict-0.2.1.dist-info/RECORD
