Metadata-Version: 2.1
Name: eazypredict
Version: 0.2.1
Summary: A python module to experiment with a bunch of machine learning algorithms on a preprocessed dataset
Home-page: https://github.com/codevardhan/EazyPredict
Author: Harshavardhan M
Author-email: harsha7vardhan@gmail.com
Project-URL: Bug Tracker, https://github.com/codevardhan/EazyPredict/issues
Classifier: Programming Language :: Python :: 3
Classifier: License :: OSI Approved :: MIT License
Classifier: Operating System :: OS Independent
Requires-Python: >=3.6
License-File: LICENSE.txt
License-File: AUTHORS.md
